SmartDiff/__init__.py
SmartDiff/globals.py
SmartDiff/main.py
SmartDiff/GUI/__init__.py
SmartDiff/GUI/step1.ui
SmartDiff/GUI/step4.ui
SmartDiff/GUI/step5.ui
SmartDiff/preprocess/__init__.py
SmartDiff/preprocess/pyexpr_formatter.py
SmartDiff/solvers/__init__.py
SmartDiff/solvers/element_op.py
SmartDiff/solvers/multivariate.py
SmartDiff/tests/__init__.py
SmartDiff/tests/high-order_test.py
SmartDiff/tests/pyexpr_formatter_test.py
SmartDiff/tests/solvers_test.py
Smartdiff-0.0.16.dist-info/LICENSE
Smartdiff-0.0.16.dist-info/METADATA
Smartdiff-0.0.16.dist-info/WHEEL
Smartdiff-0.0.16.dist-info/top_level.txt
Smartdiff-0.0.16.dist-info/RECORD
