Metadata-Version: 2.1
Name: Smartdiff
Version: 0.0.16
Summary: A smart package for Automatic Differentiation
Home-page: https://github.com/SmartDiff/cs107-FinalProject
Author: Harvard SmartDiff Group
Author-email: harvard.smartdiff@yahoo.com
License: UNKNOWN
Platform: UNKNOWN
Classifier: Programming Language :: Python :: 3
Classifier: Programming Language :: Python :: 3.6
Classifier: License :: OSI Approved :: MIT License
Classifier: Operating System :: OS Independent
Requires-Python: >=3.6
Requires-Dist: PyQt5 (==5.15.1)
Requires-Dist: numpy (>=1.9.3)
Requires-Dist: sympy (>=1.7)
